[
  {
    "model": "interactions.action",
    "fields": {
      "name": "Clic",
      "code": "click",
      "description": "El usuario hizo clic",
      "action_type": "digital"
    }
  },
  {
    "model": "interactions.action",
    "fields": {
      "name": "Visualizó página",
      "code": "page_view",
      "description": "El usuario visitó o cargó una página",
      "action_type": "digital"
    }
  },
  {
    "model": "interactions.action",
    "fields": {
      "name": "Llenó formulario",
      "code": "form_submit",
      "description": "El usuario completó un formulario",
      "action_type": "digital"
    }
  },
  {
    "model": "interactions.action",
    "fields": {
      "name": "Llamada entrante",
      "code": "incoming_call",
      "description": "El usuario llamó a la organización",
      "action_type": "telefonica"
    }
  },
  {
    "model": "interactions.action",
    "fields": {
      "name": "Asistencia a evento",
      "code": "event_attended",
      "description": "El usuario asistió a un evento",
      "action_type": "presencial"
    }
  },
  {
    "model": "interactions.action",
    "fields": {
      "name": "Sin Acción",
      "code": "no_action",
      "description": "Evento inferido o acción realizada hacia el usuario (ej: inicio de sesión, email enviado)",
      "action_type": null
    }
  },
  {
    "model": "interactions.action",
    "fields": {
      "name": "Leyó página",
      "code": "page_read",
      "description": "El usuario leyó una página de manera significativa (cumple criterios de engagement)",
      "action_type": "digital"
    }
  }
]